peforth/__init__.py
peforth/__main__.py
peforth/aiFORTH.py
peforth/hello.py
peforth/kernel.json
peforth/misc.f
peforth/peforth.f
peforth/peforth.selftest
peforth/peforthkernel.py
peforth/projectk.py
peforth/quit.f
peforth/test.py
peforth/version.txt
peforth-1.31.dist-info/LICENSE
peforth-1.31.dist-info/METADATA
peforth-1.31.dist-info/WHEEL
peforth-1.31.dist-info/top_level.txt
peforth-1.31.dist-info/RECORD
