Metadata-Version: 2.1
Name: peforth
Version: 1.31
Summary: A FORTH programming language built on python.
Home-page: https://github.com/hcchengithub/peforth
Author: H.C. Chen
Author-email: hcchen5600@gmail.com
License: The MIT License (MIT) Copyright © 2024 H.C. Chen
License-File: LICENSE
